clientdoapi/__init__.py
clientdoapi/clientdoapi.py
clientdoapi-0.0.5.dist-info/LICENSE
clientdoapi-0.0.5.dist-info/METADATA
clientdoapi-0.0.5.dist-info/WHEEL
clientdoapi-0.0.5.dist-info/top_level.txt
clientdoapi-0.0.5.dist-info/RECORD
