Metadata-Version: 2.1
Name: clientdoapi
Version: 0.0.5
Summary: A module to manage Digital Ocean API
Home-page: https://github.com/Jaxmetalmax/clientdoapi
Author: Max J. Rodriguez Beltran
Author-email: maxjrb@openitsinaloa.com
License: UNKNOWN
Project-URL: Bug Reports, https://github.com/Jaxmetalmax/clientdoapi/issues
Project-URL: Say Thanks!, https://www.openitsinaloa.com
Project-URL: Source, https://github.com/Jaxmetalmax/clientdoapi
Platform: UNKNOWN
Classifier: Programming Language :: Python :: 3.6
Classifier: License :: OSI Approved :: GNU General Public License v3 (GPLv3)
Classifier: Operating System :: OS Independent
Requires-Python: >=3.6
Requires-Dist: requests
